README.rst
setup.py
ip2location/__init__.py
ip2location/metadata.py
ip2location/scripts.py
ip2location/Provider/__init__.py
ip2location/Provider/taobao.py
ip2location/utils/__init__.py
ip2location_python.egg-info/PKG-INFO
ip2location_python.egg-info/SOURCES.txt
ip2location_python.egg-info/dependency_links.txt
ip2location_python.egg-info/requires.txt
ip2location_python.egg-info/top_level.txt
scripts/ip2location