Metadata-Version: 1.0
Name: ip2location-python
Version: 0.1.3
Summary: ipv4 to location
Home-page: https://github.com/pengyao/ip2location-python
Author: pengyao
Author-email: pengyao@pengyao.org
License: Apache License V2.0
Platform: UNKNOWN
